collibra_catalog_technical_lineage/__init__.py
collibra_catalog_technical_lineage/api_client.py
collibra_catalog_technical_lineage/configuration.py
collibra_catalog_technical_lineage/rest.py
collibra_catalog_technical_lineage/api/__init__.py
collibra_catalog_technical_lineage/api/technical_lineage_api.py
collibra_catalog_technical_lineage/models/__init__.py
test/__init__.py
test/test_technical_lineage_api.py
collibra_catalog_technical_lineage_100-1.0.0.dist-info/METADATA
collibra_catalog_technical_lineage_100-1.0.0.dist-info/WHEEL
collibra_catalog_technical_lineage_100-1.0.0.dist-info/top_level.txt
collibra_catalog_technical_lineage_100-1.0.0.dist-info/RECORD
