Metadata-Version: 2.1
Name: collibra-catalog-technical-lineage-100
Version: 1.0.0
Summary: Collibra Catalog Technical Lineage API
Home-page: 
Author-email: 
Keywords: Swagger,Collibra Catalog Technical Lineage API
Requires-Dist: urllib3 (>=1.15)
Requires-Dist: six (>=1.10)
Requires-Dist: certifi
Requires-Dist: python-dateutil
